procciao/README.MD
procciao/__init__.py
procciao/procdict.py
procciao/requirements.txt
procciao/savebase64.py
procciao/thirdparty.json
procciao-0.13.dist-info/LICENSE.rst
procciao-0.13.dist-info/METADATA
procciao-0.13.dist-info/WHEEL
procciao-0.13.dist-info/top_level.txt
procciao-0.13.dist-info/RECORD
