Metadata-Version: 2.1
Name: procciao
Version: 0.13
Summary: A library for killing processes/subprocesses the most gracefully way possible
Home-page: https://github.com/hansalemaos/procciao
Author: Johannes Fischer
Author-email: aulasparticularesdealemaosp@gmail.com
License: MIT
Keywords: killing,pid
Classifier: Development Status :: 4 - Beta
Classifier: Programming Language :: Python :: 3 :: Only
Classifier: Programming Language :: Python :: 3.10
Classifier: Topic :: Software Development :: Libraries :: Python Modules
Classifier: Topic :: Utilities
License-File: LICENSE.rst
Requires-Dist: consolectrlchandler
Requires-Dist: flatten-any-dict-iterable-or-whatsoever
Requires-Dist: flatten-everything
Requires-Dist: pidconnectioninfos
Requires-Dist: touchtouch
Requires-Dist: wmicprocsdict
